mom/Choices.py
mom/Digraph.py
mom/GraphBuilder.py
mom/MainClasses.py
mom/MatrixChoices.py
mom/Test.py
mom/__init__.py
mom/__main__.py
mom/testGUI.py
matrix_odin_morphology-0.0.1.dist-info/LICENSE
matrix_odin_morphology-0.0.1.dist-info/METADATA
matrix_odin_morphology-0.0.1.dist-info/WHEEL
matrix_odin_morphology-0.0.1.dist-info/top_level.txt
matrix_odin_morphology-0.0.1.dist-info/RECORD
