Metadata-Version: 2.1
Name: matrix-odin-morphology
Version: 0.0.1
Summary: A software for inferring morphological rules from linguistically annotated data
Home-page: https://github.com/pypa/sampleproject
Author: Elizabeth Conrad
Author-email: ecconrad@uw.edu
License: UNKNOWN
Platform: UNKNOWN
Classifier: Programming Language :: Python :: 3
Classifier: License :: OSI Approved :: MIT License
Classifier: Operating System :: OS Independent
Classifier: Development Status :: 3 - Alpha
Requires-Python: >=3.6
License-File: LICENSE
